distributed_asgi/__init__.py
distributed_asgi/common.py
distributed_asgi/consumer.py
distributed_asgi/producer.py
distributed_asgi-0.0.2.dev0.dist-info/METADATA
distributed_asgi-0.0.2.dev0.dist-info/RECORD
distributed_asgi-0.0.2.dev0.dist-info/WHEEL
distributed_asgi-0.0.2.dev0.dist-info/top_level.txt
