Metadata-Version: 2.1
Name: distributed-asgi
Version: 0.0.2.dev0
Summary: Create distributed ASGI applications that pull events from a central Redis queue.
Home-page: UNKNOWN
Author: Ian Murphy
Author-email: 3jackdaws@gmail.com
License: MIT
Platform: UNKNOWN
Classifier: Programming Language :: Python :: 3
Classifier: License :: OSI Approved :: MIT License
Classifier: Operating System :: OS Independent
Requires-Dist: aioredis
